bluesky_cartpole/__init__.py
bluesky_cartpole/_version.py
bluesky_cartpole/cartpole.py
bluesky_cartpole/cartpole_plan.py
bluesky_cartpole/run_cartpole.py
bluesky_cartpole/tests/__init__.py
bluesky_cartpole/tests/conftest.py
bluesky_cartpole/tests/test_cartpole.py
bluesky_cartpole-0.1.0.dist-info/AUTHORS.rst
bluesky_cartpole-0.1.0.dist-info/LICENSE
bluesky_cartpole-0.1.0.dist-info/METADATA
bluesky_cartpole-0.1.0.dist-info/WHEEL
bluesky_cartpole-0.1.0.dist-info/entry_points.txt
bluesky_cartpole-0.1.0.dist-info/top_level.txt
bluesky_cartpole-0.1.0.dist-info/RECORD
