Metadata-Version: 2.1
Name: bluesky-cartpole
Version: 0.1.0
Summary: Train a cartpole agent with bluesky and ophyd!
Home-page: https://github.com/bluesky/bluesky-cartpole
Author: Brookhaven National Lab
License: BSD (3-clause)
Platform: UNKNOWN
Classifier: Development Status :: 2 - Pre-Alpha
Classifier: Natural Language :: English
Classifier: Programming Language :: Python :: 3
Requires-Python: >=3.6
License-File: LICENSE
License-File: AUTHORS.rst
Requires-Dist: setuptools (>=47.1.1)
Requires-Dist: gym (==0.18.0)
Requires-Dist: tensorflow (==2.5.1)
Requires-Dist: tensorforce (==0.5.5)
Requires-Dist: bluesky (==1.6.7)
Requires-Dist: bluesky-adaptive (==0.1.0)
Requires-Dist: ophyd (==1.6.0)
Requires-Dist: databroker (==1.2.0)
Requires-Dist: intake (==0.6.0)
